CHANGELOG.rst
MANIFEST.in
README.md
setup.cfg
setup.py
kloudi/__init__.py
kloudi.egg-info/PKG-INFO
kloudi.egg-info/SOURCES.txt
kloudi.egg-info/dependency_links.txt
kloudi.egg-info/not-zip-safe
kloudi.egg-info/requires.txt
kloudi.egg-info/top_level.txt
kloudi/aws/__init__.py
kloudi/aws/ec2/__init__.py
kloudi/aws/ec2/ebs.py
kloudi/aws/ec2/elb.py
kloudi/aws/ec2/instances.py
kloudi/aws/ec2/security_groups.py
kloudi/aws/route53/__init__.py
kloudi/aws/route53/hostedzone.py
kloudi/aws/s3/__init__.py
kloudi/aws/s3/bucket.py
kloudi/utils/__init__.py
kloudi/utils/accounts.py
kloudi/utils/config.py
kloudi/utils/graphite.py
kloudi/utils/logging.py
kloudi/utils/naming.py
kloudi/utils/tagger.py
kloudi/utils/jgp/__init__.py
kloudi/utils/jgp/gen_entry.py
kloudi/utils/jgp/statement.py
scripts/kloudiEC2.py
scripts/kloudiS3.py
scripts/kloudinv2route53.py