Metadata-Version: 1.1
Name: kloudi
Version: 0.2
Summary: kloudi - Provisions AWS services from easy to read ini configs
Home-page: https://github.com/jesco39/kloudi
Author: Jesse Escobedo
Author-email: jesse@moda.bz
License: Apache
Keywords: kloudi C3 AWS automation cloud devops
Platform: UNKNOWN
Classifier: Programming Language :: Python
Classifier: Programming Language :: Python :: 2.6
Classifier: Programming Language :: Python :: 2.7
Classifier: Intended Audience :: System Administrators 
